<annotation>
	<folder>Liang</folder>
	<filename>image286.png</filename>
	<path>C:\Users\Ming En\Desktop\Liang\image286.png</path>
	<source>
		<database>Unknown</database>
	</source>
	<size>
		<width>180</width>
		<height>50</height>
		<depth>3</depth>
	</size>
	<segmented>0</segmented>
	<object>
		<name>D</name>
		<pose>Unspecified</pose>
		<truncated>0</truncated>
		<difficult>0</difficult>
		<bndbox>
			<xmin>8</xmin>
			<ymin>13</ymin>
			<xmax>42</xmax>
			<ymax>42</ymax>
		</bndbox>
	</object>
	<object>
		<name>8</name>
		<pose>Unspecified</pose>
		<truncated>0</truncated>
		<difficult>0</difficult>
		<bndbox>
			<xmin>43</xmin>
			<ymin>14</ymin>
			<xmax>70</xmax>
			<ymax>44</ymax>
		</bndbox>
	</object>
	<object>
		<name>K</name>
		<pose>Unspecified</pose>
		<truncated>0</truncated>
		<difficult>0</difficult>
		<bndbox>
			<xmin>78</xmin>
			<ymin>13</ymin>
			<xmax>112</xmax>
			<ymax>42</ymax>
		</bndbox>
	</object>
	<object>
		<name>N</name>
		<pose>Unspecified</pose>
		<truncated>0</truncated>
		<difficult>0</difficult>
		<bndbox>
			<xmin>112</xmin>
			<ymin>9</ymin>
			<xmax>148</xmax>
			<ymax>40</ymax>
		</bndbox>
	</object>
	<object>
		<name>K</name>
		<pose>Unspecified</pose>
		<truncated>0</truncated>
		<difficult>0</difficult>
		<bndbox>
			<xmin>149</xmin>
			<ymin>9</ymin>
			<xmax>174</xmax>
			<ymax>37</ymax>
		</bndbox>
	</object>
</annotation>
