<annotation>
	<folder>Liang</folder>
	<filename>image248.png</filename>
	<path>C:\Users\Ming En\Desktop\Liang\image248.png</path>
	<source>
		<database>Unknown</database>
	</source>
	<size>
		<width>180</width>
		<height>50</height>
		<depth>3</depth>
	</size>
	<segmented>0</segmented>
	<object>
		<name>K</name>
		<pose>Unspecified</pose>
		<truncated>1</truncated>
		<difficult>0</difficult>
		<bndbox>
			<xmin>11</xmin>
			<ymin>21</ymin>
			<xmax>43</xmax>
			<ymax>50</ymax>
		</bndbox>
	</object>
	<object>
		<name>D</name>
		<pose>Unspecified</pose>
		<truncated>0</truncated>
		<difficult>0</difficult>
		<bndbox>
			<xmin>43</xmin>
			<ymin>15</ymin>
			<xmax>77</xmax>
			<ymax>42</ymax>
		</bndbox>
	</object>
	<object>
		<name>H</name>
		<pose>Unspecified</pose>
		<truncated>0</truncated>
		<difficult>0</difficult>
		<bndbox>
			<xmin>79</xmin>
			<ymin>10</ymin>
			<xmax>114</xmax>
			<ymax>43</ymax>
		</bndbox>
	</object>
	<object>
		<name>Q</name>
		<pose>Unspecified</pose>
		<truncated>0</truncated>
		<difficult>0</difficult>
		<bndbox>
			<xmin>116</xmin>
			<ymin>10</ymin>
			<xmax>151</xmax>
			<ymax>47</ymax>
		</bndbox>
	</object>
	<object>
		<name>A</name>
		<pose>Unspecified</pose>
		<truncated>0</truncated>
		<difficult>0</difficult>
		<bndbox>
			<xmin>148</xmin>
			<ymin>7</ymin>
			<xmax>174</xmax>
			<ymax>34</ymax>
		</bndbox>
	</object>
</annotation>
